LICENSE.txt
MANIFEST.in
README.rst
setup.py
analytics_kits/__init__.py
analytics_kits/admin.py
analytics_kits/apps.py
analytics_kits/forms.py
analytics_kits/models.py
analytics_kits/settings.py
analytics_kits/utils.py
analytics_kits/management/__init__.py
analytics_kits/management/commands/__init__.py
analytics_kits/management/commands/analytics_results.py
analytics_kits/migrations/0001_initial.py
analytics_kits/migrations/0002_delete_analyiticskitsmixin.py
analytics_kits/migrations/__init__.py
django_analytics_kits.egg-info/PKG-INFO
django_analytics_kits.egg-info/SOURCES.txt
django_analytics_kits.egg-info/dependency_links.txt
django_analytics_kits.egg-info/requires.txt
django_analytics_kits.egg-info/top_level.txt
tests/__init__.py
tests/models.py
tests/test_settings.py
tests/tests.py