Metadata-Version: 1.1
Name: django-analytics-kits
Version: 0.1.7
Summary: A Django app to get analytics data from Google Analytics and save them in other django app models
Home-page: https://github.com/smallmedia/django-analytics-kits
Author: SmallMediaLab
Author-email: lab@smallmedia.org.uk
License: New BSD
Platform: UNKNOWN
Classifier: Environment :: Web Environment
Classifier: Framework :: Django
Classifier: Intended Audience :: Developers
Classifier: Operating System :: OS Independent
Classifier: Programming Language :: Python
